zephyrus/XUV_flux.py
zephyrus/__init__.py
zephyrus/constants.py
zephyrus/escape.py
zephyrus/planets_parameters.py
zephyrus/data/Johnstone_2021/0p5Msun_50percentile_basic.dat
zephyrus/data/Johnstone_2021/0p7Msun_50percentile_basic.dat
zephyrus/data/Johnstone_2021/1p0Msun_1p0OmegaSun_basic.dat
zephyrus/data/Johnstone_2021/1p0Msun_50percentile_basic.dat
fwl_zephyrus-25.3.11.dist-info/LICENSE.md
fwl_zephyrus-25.3.11.dist-info/METADATA
fwl_zephyrus-25.3.11.dist-info/WHEEL
fwl_zephyrus-25.3.11.dist-info/top_level.txt
fwl_zephyrus-25.3.11.dist-info/RECORD
