Metadata-Version: 2.2
Name: fwl-zephyrus
Version: 25.3.11
Summary: Atmospheric escape models of exoplanets.
Author-email: Emma Postolec <e.n.postolec@rug.nl>, Tim Lichtenberg <tim.lichtenberg@rug.nl>, Laurent Soucasse <l.soucasse@esciencecenter.nl>, Harrison Nicholls <harrison.nicholls@physics.ox.ac.uk>
License: Apache 2.0 License
Project-URL: homepage, https://github.com/FormingWorlds/ZEPHYRUS
Keywords: exoplanet,escape
Classifier: Intended Audience :: Science/Research
Classifier: License :: OSI Approved :: Apache Software License
Classifier: Operating System :: MacOS :: MacOS X
Classifier: Operating System :: POSIX :: Linux
Classifier: Programming Language :: Python :: 3
Requires-Python: >=3.10
License-File: LICENSE.md
Requires-Dist: fwl-mors>=24.11.18
Requires-Dist: matplotlib
Requires-Dist: numpy
Provides-Extra: develop
Requires-Dist: bump-my-version; extra == "develop"
Requires-Dist: coverage[toml]; extra == "develop"
Requires-Dist: pytest; extra == "develop"
Provides-Extra: docs
Requires-Dist: markdown-include; extra == "docs"
Requires-Dist: mkdocs; extra == "docs"
Requires-Dist: mkdocs-material; extra == "docs"
Requires-Dist: mkdocstrings[python]; extra == "docs"
Provides-Extra: publishing
Requires-Dist: twine; extra == "publishing"
Requires-Dist: wheel; extra == "publishing"
Requires-Dist: build; extra == "publishing"
